Lathe/Runtime.py
Lathe/__init__.py
PyLathe-0.1.0.dist-info/LICENSE.txt
PyLathe-0.1.0.dist-info/METADATA
PyLathe-0.1.0.dist-info/WHEEL
PyLathe-0.1.0.dist-info/top_level.txt
PyLathe-0.1.0.dist-info/RECORD
