Metadata-Version: 2.1
Name: PyLathe
Version: 0.1.0
Summary: A Python Wrapper for Lathe
Home-page: https://github.com/emmettgb/PyLathe
Author: Emmett Boudreau
Author-email: emmettgb@gmail.com
License: UNKNOWN
Platform: UNKNOWN
Classifier: Programming Language :: Python :: 3
Classifier: License :: OSI Approved :: MIT License
Classifier: Operating System :: OS Independent
Requires-Python: >=3.6
